ClientKit/DeviceAuth.py
ClientKit/UserData.py
ClientKit/__init__.py
playdionclientkit-2025.5.12.post1.dist-info/licenses/LICENSE
playdionclientkit-2025.5.12.post1.dist-info/METADATA
playdionclientkit-2025.5.12.post1.dist-info/WHEEL
playdionclientkit-2025.5.12.post1.dist-info/top_level.txt
playdionclientkit-2025.5.12.post1.dist-info/RECORD
