Metadata-Version: 2.4
Name: PlaydionClientKit
Version: 2025.5.12.post1
Summary: ClientKit for Playdion Client
Home-page: https://github.com/AdrianDevProjects/ClientKit
Author: Adrian Albrecht
Author-email: adriandevprojects@gmail.com
License: GPL-3.0
License-File: LICENSE
Requires-Dist: requests
Requires-Dist: pathlib2
Dynamic: author
Dynamic: author-email
Dynamic: description
Dynamic: description-content-type
Dynamic: home-page
Dynamic: license
Dynamic: license-file
Dynamic: requires-dist
Dynamic: summary
